promptflow/_constants.py
promptflow/_core/__init__.py
promptflow/_core/_errors.py
promptflow/_core/cache_manager.py
promptflow/_core/connection_manager.py
promptflow/_core/data/tool.schema.json
promptflow/_core/entry_meta_generator.py
promptflow/_core/flow_execution_context.py
promptflow/_core/log_manager.py
promptflow/_core/metric_logger.py
promptflow/_core/operation_context.py
promptflow/_core/run_tracker.py
promptflow/_core/token_provider.py
promptflow/_core/tool.py
promptflow/_core/tool_meta_generator.py
promptflow/_core/tool_settings_parser.py
promptflow/_core/tool_validation.py
promptflow/_core/tools_manager.py
promptflow/_utils/__init__.py
promptflow/_utils/_errors.py
promptflow/_utils/anti_ssrf/__init__.py
promptflow/_utils/anti_ssrf/anti_ssrf.py
promptflow/_utils/anti_ssrf/anti_ssrf_policy.py
promptflow/_utils/anti_ssrf/cidr_helpers.py
promptflow/_utils/anti_ssrf/exceptions.py
promptflow/_utils/async_utils.py
promptflow/_utils/connection_utils.py
promptflow/_utils/context_utils.py
promptflow/_utils/credential_scrubber.py
promptflow/_utils/credential_utils.py
promptflow/_utils/dataclass_serializer.py
promptflow/_utils/exception_utils.py
promptflow/_utils/execution_utils.py
promptflow/_utils/feature_utils.py
promptflow/_utils/flow_utils.py
promptflow/_utils/inputs_mapping_utils.py
promptflow/_utils/load_data.py
promptflow/_utils/logger_utils.py
promptflow/_utils/multimedia_data_converter.py
promptflow/_utils/multimedia_utils.py
promptflow/_utils/process_utils.py
promptflow/_utils/retry_utils.py
promptflow/_utils/run_tracker_utils.py
promptflow/_utils/thread_utils.py
promptflow/_utils/tool_utils.py
promptflow/_utils/user_agent_utils.py
promptflow/_utils/utils.py
promptflow/_utils/yaml_utils.py
promptflow/connections/__init__.py
promptflow/constants.py
promptflow/contracts/__init__.py
promptflow/contracts/_errors.py
promptflow/contracts/_run_management.py
promptflow/contracts/flow.py
promptflow/contracts/multimedia.py
promptflow/contracts/run_info.py
promptflow_core-1.18.2.dist-info/METADATA
promptflow_core-1.18.2.dist-info/WHEEL
promptflow_core-1.18.2.dist-info/RECORD
