Metadata-Version: 2.4
Name: promptflow-core
Version: 1.18.2
Summary: Prompt flow core
License: MIT
Keywords: core
Author: Microsoft Corporation
Author-email: aml-pt-eng@microsoft.com
Requires-Python: >=3.9,<4.0
Classifier: License :: OSI Approved :: MIT License
Classifier: Operating System :: OS Independent
Classifier: Programming Language :: Python
Classifier: Programming Language :: Python :: 3
Classifier: Programming Language :: Python :: 3.9
Classifier: Programming Language :: Python :: 3.10
Classifier: Programming Language :: Python :: 3.11
Classifier: Programming Language :: Python :: 3.12
Classifier: Programming Language :: Python :: 3.13
Classifier: Programming Language :: Python :: 3.14
Classifier: Programming Language :: Python :: 3 :: Only
Provides-Extra: azureml-serving
Provides-Extra: executor-service
Requires-Dist: azure-ai-ml (>=1.14.0,<2.0.0) ; extra == "azureml-serving"
Requires-Dist: azure-identity (>=1.12.0,<2.0.0) ; extra == "azureml-serving"
Requires-Dist: azureml-ai-monitoring (>=0.1.0b3,<1.0.0) ; extra == "azureml-serving"
Requires-Dist: docstring_parser
Requires-Dist: fastapi (>=0.109.0,<1.0.0)
Requires-Dist: filetype (>=1.2.0)
Requires-Dist: flask (>=2.2.3,<4.0.0)
Requires-Dist: jsonschema (>=4.0.0,<5.0.0)
Requires-Dist: promptflow-tracing (==1.18.2)
Requires-Dist: psutil
Requires-Dist: python-dateutil (>=2.1.0,<3.0.0)
Requires-Dist: ruamel.yaml (>=0.17.10,<1.0.0)
Requires-Dist: starlette (>=0.49.1,<0.50.0)
Project-URL: Bug Reports, https://github.com/microsoft/promptflow/issues
Project-URL: Homepage, https://microsoft.github.io/promptflow/
Project-URL: Repository, https://github.com/microsoft/promptflow
